[
  {
    "Type": "DataTable",
    "Name": "SECTOR_GRADE_107003020",
    "Class": "UScriptClass'DataTable'",
    "Properties": {
      "RowStruct": {
        "ObjectName": "ScriptStruct'SectorGradeTemplate'",
        "ObjectPath": "/Script/MirMobile"
      }
    },
    "Rows": {
      "1": {
        "SectorID": 1030030101,
        "SectorRange": 3054.0,
        "SectorLocation": {
          "X": -521.477,
          "Y": 15072.247,
          "Z": 4007.938
        }
      },
      "2": {
        "SectorID": 1030030102,
        "SectorRange": 3000.0,
        "SectorLocation": {
          "X": 19149.578,
          "Y": 12274.587,
          "Z": 298.875
        }
      },
      "3": {
        "SectorID": 1030030103,
        "SectorRange": 3523.0,
        "SectorLocation": {
          "X": -22002.412,
          "Y": 14684.013,
          "Z": 298.875
        }
      },
      "4": {
        "SectorID": 1030030103,
        "SectorRange": 3539.0,
        "SectorLocation": {
          "X": 6753.188,
          "Y": -8751.725,
          "Z": 529.5
        }
      }
    }
  }
]