[
  {
    "Type": "DataTable",
    "Name": "MAP_MINI_300240",
    "Class": "UScriptClass'DataTable'",
    "Properties": {
      "RowStruct": {
        "ObjectName": "ScriptStruct'MapMiniInfoTemplate'",
        "ObjectPath": "/Script/MirMobile"
      }
    },
    "Rows": {
      "1": {
        "Name": 1,
        "InfoMainType": "EMapMiniInfoMainType::Default",
        "InfoSubType": 2,
        "InfoSubTypeValue": 0,
        "InfoValue": 40802,
        "DetailInfoValue": 0,
        "InfoStringId": 420003,
        "InfoStringPosType": "EMapMiniInfoStringPosType::Bottom",
        "InfoCoordinate": {
          "X": -8542.707,
          "Y": 10003.136,
          "Z": 10.00061
        }
      }
    }
  }
]